Metadata-Version: 2.1
Name: aireplication
Version: 0.0.4
Summary: Private API for Andrew
Home-page: https://github.com/andrewlee1807/ai-replicate
Author: Andrew
Author-email: andrewlee1807@gmail.com
License: Apache-2.0 license
Keywords: python,blackhole,aireplication
Platform: UNKNOWN
Classifier: Development Status :: 3 - Alpha
Classifier: Intended Audience :: Education
Classifier: Programming Language :: Python :: 3
Classifier: Operating System :: MacOS :: MacOS X
Classifier: Operating System :: Microsoft :: Windows
License-File: LICENSE
